wbe/__init__.py
wbe/emulator.py
wbe/version.py
wbe-0.0.1.dist-info/METADATA
wbe-0.0.1.dist-info/WHEEL
wbe-0.0.1.dist-info/top_level.txt
wbe-0.0.1.dist-info/RECORD
