Metadata-Version: 2.1
Name: wbe
Version: 0.0.1
Summary: Brain emulation with a convenient pip install
Author: AGI
Maintainer: AGI
License: Apache-2.0
Platform: Windows
Platform: POSIX
Platform: MacOSX
Classifier: Programming Language :: Python :: 3
Classifier: Programming Language :: Python :: 3.6
Classifier: Programming Language :: Python :: 3.7
Classifier: License :: OSI Approved :: Apache Software License
Classifier: Operating System :: OS Independent
Requires-Dist: Pillow
